<?xml version="1.0" encoding="utf-8" ?><dwsync><file name="kv_sp.jpg" server="users704.lolipop.jp" local="3635309774" remote="3676241940" Dst="-1" /><file name="fandiv.jpg" server="users704.lolipop.jp" local="3635307586" remote="3676241940" Dst="-1" /><file name="tel.png" server="users704.lolipop.jp" local="3635307584" remote="3676241940" Dst="-1" /><file name="kv_nimaiiwa.jpg" server="users704.lolipop.jp" local="3635307584" remote="3676241940" Dst="-1" /><file name="suinoujima_sp.jpg" server="users704.lolipop.jp" local="3635307586" remote="3676241940" Dst="-1" /><file name="logo_black.png" server="users704.lolipop.jp" local="3635309078" remote="3676241940" Dst="-1" /><file name="div_ico.png" server="users704.lolipop.jp" local="3635307585" remote="3676241940" Dst="-1" /><file name="yonaguni_sp.jpg" server="users704.lolipop.jp" local="3635307720" remote="3676241940" Dst="-1" /><file name="errors.txt" server="users704.lolipop.jp" local="3635307583" remote="3676241940" Dst="-1" /><file name="kerama_pc.jpg" server="users704.lolipop.jp" local="3635307585" remote="3676241940" Dst="-1" /><file name="zamami_pc.jpg" server="users704.lolipop.jp" local="3635307585" remote="3676241940" Dst="-1" /><file name="china_ico.png" server="users704.lolipop.jp" local="3635307585" remote="3676241940" Dst="-1" /><file name="weibo.png" server="users704.lolipop.jp" local="3635307584" remote="3676241940" Dst="-1" /><file name="face.png" server="users704.lolipop.jp" local="3635307585" remote="3676241940" Dst="-1" /><file name="aonodoukutu_pc.jpg" server="users704.lolipop.jp" local="3635307585" remote="3676241940" Dst="-1" /><file name="miyako_pc.jpg" server="users704.lolipop.jp" local="3638834817" remote="3676241940" Dst="-1" /><file name="kv_suinou.jpg" server="users704.lolipop.jp" local="3635307584" remote="3676241940" Dst="-1" /><file name="logo.png" server="users704.lolipop.jp" local="3635307584" remote="3676241940" Dst="-1" /><file name="zamami_sp.jpg" server="users704.lolipop.jp" local="3635307586" remote="3676241940" Dst="-1" /><file name="kv_saihoku.jpg" server="users704.lolipop.jp" local="3635307584" remote="3676241940" Dst="-1" /><file name="license.jpg" server="users704.lolipop.jp" local="3635307586" remote="3676241940" Dst="-1" /><file name="Twitter.png" server="users704.lolipop.jp" local="3635307584" remote="3676241940" Dst="-1" /><file name="aonodoukutu_sp.jpg" server="users704.lolipop.jp" local="3635307586" remote="3676241940" Dst="-1" /><file name="miyako_sp.jpg" server="users704.lolipop.jp" local="3635802317" remote="3676241940" Dst="-1" /><file name="diver_ico.png" server="users704.lolipop.jp" local="3635307585" remote="3676241940" Dst="-1" /><file name="facebook.png" server="users704.lolipop.jp" local="3635307584" remote="3676241940" Dst="-1" /><file name="kerama_sp.jpg" server="users704.lolipop.jp" local="3635802659" remote="3676241940" Dst="-1" /><file name="yonaguni_pc.jpg" server="users704.lolipop.jp" local="3637182373" remote="3676241940" Dst="-1" /><file name="taiken.jpg" server="users704.lolipop.jp" local="3635307586" remote="3676241940" Dst="-1" /><file name="suinoujima_pc.jpg" server="users704.lolipop.jp" local="3635307585" remote="3676241940" Dst="-1" /></dwsync>